django_tree-0.6.2.dist-info/licenses/LICENSE
tree/__init__.py
tree/apps.py
tree/fields.py
tree/forms.py
tree/lookups.py
tree/models.py
tree/operations.py
tree/query.py
tree/signals.py
tree/transforms.py
tree/types.py
tree/migrations/0001_initial.py
tree/migrations/0002_remove_old_functions.py
tree/migrations/__init__.py
tree/sql/__init__.py
tree/sql/base.py
tree/sql/postgresql.py
django_tree-0.6.2.dist-info/METADATA
django_tree-0.6.2.dist-info/WHEEL
django_tree-0.6.2.dist-info/top_level.txt
django_tree-0.6.2.dist-info/RECORD
