Metadata-Version: 2.4
Name: django-tree
Version: 0.6.2
Summary: Fast and easy tree structures.
Author-email: Bertrand Bordage <bordage.bertrand@gmail.com>
License-Expression: BSD-2-Clause
Project-URL: Repository, https://github.com/BertrandBordage/django-tree
Classifier: Development Status :: 3 - Alpha
Classifier: Framework :: Django
Classifier: Intended Audience :: Developers
Classifier: Operating System :: OS Independent
Classifier: Programming Language :: Python :: 3
Classifier: Programming Language :: Python :: 3.6
Classifier: Programming Language :: Python :: 3.7
Classifier: Programming Language :: Python :: 3.8
Classifier: Programming Language :: Python :: 3.9
Classifier: Programming Language :: Python :: 3.10
Classifier: Programming Language :: Python :: 3.11
Classifier: Topic :: Internet :: WWW/HTTP
Requires-Python: >=3.6
License-File: LICENSE
Requires-Dist: Django>=3.2
Dynamic: license-file
